Metadata-Version: 2.1
Name: packageshree
Version: 0.3
Summary: An demonstration of how to create, document, and publish 
Author: Shridhar
Author-email: shridhar5697@gmail.com
License-File: Licence.txt.txt
